{"game":{"id":1019450,"name":"Table Manners: Physics-Based Dating Game","type":"game","thumbnail":"https:\/\/cdn.akamai.steamstatic.com\/steam\/apps\/1019450\/header.jpg?t=1634658448","genres":["Simulation"],"categories":["Single-player","Steam Achievements","Partial Controller Support"],"tags":["Simulation","Dating Sim","Intentionally Awkward Controls","Comedy","Physics","Funny","First-Person"],"store_available":true,"in_store":true,"rating":{"overall":["Mixed"],"recent":[""],"updated":1697872028},"age_rating":0,"release_date":"14 Feb, 2020","url":"http:\/\/store.steampowered.com\/app\/1019450\/","crossover":{"url":"<a href=\"https:\/\/www.codeweavers.com\/compatibility\/crossover\/Table-Manners-Physics-Based-Dating-Game\">Table-Manners-Physics-Based-Dating-Game<\/a>","valid":false,"compatibility":" ","breakdown":" "}}}