{"game":{"id":1775270,"name":"The Dark Pictures Anthology: House of Ashes - Friend's Pass","type":"game","thumbnail":"https:\/\/cdn.akamai.steamstatic.com\/steam\/apps\/1775270\/header.jpg?t=1643385626","genres":["Action","Adventure"],"categories":["Multi-player","PvP","Online PvP","Full controller support","Remote Play Together"],"tags":["Action","Adventure","Action-Adventure","Realistic","Third Person","Atmospheric","Dark Fantasy","Horror","PvP","Choices Matter","Violent","Multiple Endings","Gore","Story Rich","Co-op Campaign","Online Co-Op","Dark"],"store_available":true,"in_store":true,"rating":{"overall":["Mixed"],"recent":[""],"updated":1697918046},"age_rating":0,"release_date":"28 Jan, 2022","url":"http:\/\/store.steampowered.com\/app\/1775270\/","crossover":{"url":"<a href=\"https:\/\/www.codeweavers.com\/compatibility\/crossover\/The-Dark-Pictures-Anthology-House-of-Ashes---Friends-Pass\">The-Dark-Pictures-Anthology-House-of-Ashes---Friends-Pass<\/a>","valid":false,"compatibility":" ","breakdown":" "}}}