{"game":{"id":1976950,"name":"Desktop Dungeons: Rewind","type":"game","thumbnail":"https:\/\/cdn.akamai.steamstatic.com\/steam\/apps\/1976950\/header.jpg?t=1697553447","genres":["Adventure","Indie","Strategy"],"categories":["Single-player","Steam Achievements","Steam Cloud","Steam Leaderboards"],"tags":["Turn-Based","Roguelike","Puzzle","Fantasy","Comedy","Difficult","Roguelite","Isometric","Tactical RPG","Resource Management","Top-Down","Replay Value","Dungeon Crawler","Procedural Generation","Turn-Based Strategy","Turn-Based Tactics","Loot","Remake","Traditional Roguelike","Soundtrack"],"store_available":true,"in_store":true,"rating":{"overall":["Mostly Positive"],"recent":[""],"updated":1697913278},"age_rating":0,"release_date":"18 Apr, 2023","url":"http:\/\/store.steampowered.com\/app\/1976950\/","crossover":{"url":"<a href=\"https:\/\/www.codeweavers.com\/compatibility\/crossover\/Desktop-Dungeons-Rewind\">Desktop-Dungeons-Rewind<\/a>","valid":true,"compatibility":"<ul class=\"star-rating-table\"><li class=\"active\"><i class=\"fas fa-star\"><\/i><\/li><li class=\"active\"><i class=\"fas fa-star\"><\/i><\/li><li class=\"active\"><i class=\"fas fa-star\"><\/i><\/li><li class=\"active\"><i class=\"fas fa-star\"><\/i><\/li><li class=\"active\"><i class=\"fas fa-star\"><\/i><\/li><\/ul><\/span>","breakdown":"\n<div class=\"container py-5\">\n    <h2 class=\"txt_magenta\"><i class=\"fad fa-medal fa-3x vertical-align-middle rotate-3deg\"><\/i> Desktop Dungeons: Rewind Rating Breakdown<\/h2>\n    <span id=\"var_app_id\" class=\"noshow\">19634<\/span>\n    <span id=\"var_app_plnk\" class=\"noshow\">Desktop-Dungeons-Rewind<\/span>\n    <p>\n        This is a breakdown of ratings by CrossOver Version.\n        The most recent version is always used on the application overview page.<br>\n        Click on a version to view ranks submitted to it.<br>\n        <a href=\"\/compatibility\/rating-system\"><i class=\"fas fa-info-circle\"><\/i> About the Rating System<\/a>\n    <\/p>\n\n\n    \n<div id=\"row_117053\" class=\"breakdown-row card card-light noshow\">\n    <div class=\"card-header showMedal cursor bold\">\n        <ul class=\"star-rating-table\"><li class=\"active\"><i class=\"fas fa-star\"><\/i><\/li><li class=\"active\"><i class=\"fas fa-star\"><\/i><\/li><li class=\"active\"><i class=\"fas fa-star\"><\/i><\/li><li class=\"active\"><i class=\"fas fa-star\"><\/i><\/li><li class=\"active\"><i class=\"fas fa-star\"><\/i><\/li><\/ul>\n        23.0.0  &middot;\n        <i class=\"fab fa-apple\"><\/i> macOS\n        <!-- but_117053 -->\n    <\/div>\n    <div id=\"area_117053\" class=\"card-body noshow\">\n        <table id=\"body_117053\" class=\"frame\" style=\"width:100%;\">\n        <\/table>\n    <\/div>\n<\/div>\n\n<div id=\"row_107563\" class=\"breakdown-row card card-light noshow\">\n    <div class=\"card-header showMedal cursor bold\">\n        <ul class=\"star-rating-table\"><li class=\"active\"><i class=\"fas fa-star\"><\/i><\/li><li class=\"active\"><i class=\"fas fa-star\"><\/i><\/li><li class=\"active\"><i class=\"fas fa-star\"><\/i><\/li><li class=\"active\"><i class=\"fas fa-star\"><\/i><\/li><li><i class=\"far fa-star\"><\/i><\/li><\/ul>\n        22.1.1  &middot;\n        <i class=\"fab fa-apple\"><\/i> macOS\n        <!-- but_107563 -->\n    <\/div>\n    <div id=\"area_107563\" class=\"card-body noshow\">\n        <table id=\"body_107563\" class=\"frame\" style=\"width:100%;\">\n        <\/table>\n    <\/div>\n<\/div>\n\n\n    <p class=\"mt-2\"><a href=\"#\" id=\"breakdown-showall\" class=\"noshow\"><i class=\"fas fa-chevron-square-down\"><\/i> Show More...<\/a><\/p>\n<\/div>\n<\/div>\n\n\n"}}}