{"game":{"id":244890,"name":"Velocity\u00aeUltra","type":"game","thumbnail":"https:\/\/cdn.akamai.steamstatic.com\/steam\/apps\/244890\/header.jpg?t=1634659330","genres":["Action","Indie"],"categories":["Single-player","Steam Achievements","Full controller support","Steam Trading Cards","Steam Cloud","Steam Leaderboards"],"tags":["Action","Indie","Shoot 'Em Up","Female Protagonist","2D"],"store_available":true,"in_store":true,"rating":{"overall":["Very Positive"],"recent":[""],"updated":1697863007},"age_rating":0,"release_date":"12 Dec, 2013","url":"http:\/\/store.steampowered.com\/app\/244890\/","crossover":{"url":"<a href=\"https:\/\/www.codeweavers.com\/compatibility\/crossover\/VelocityUltra\">VelocityUltra<\/a>","valid":false,"compatibility":" ","breakdown":" "}}}