{"game":{"id":251470,"name":"TowerFall Ascension","type":"game","thumbnail":"https:\/\/cdn.akamai.steamstatic.com\/steam\/apps\/251470\/header.jpg?t=1690839807","genres":["Action","Indie"],"categories":["Single-player","Multi-player","PvP","Shared\/Split Screen PvP","Co-op","Shared\/Split Screen Co-op","Shared\/Split Screen","Steam Achievements","Full controller support","Steam Trading Cards","Steam Cloud","Stats","Remote Play on Phone","Remote Play on Tablet","Remote Play on TV","Remote Play Together"],"tags":["Local Multiplayer","Indie","2D Fighter","Action","Local Co-Op","Pixel Graphics","Platformer","4 Player Local","Multiplayer","2D","Co-op","Arcade","Controller","Fighting","Adventure","Retro","Party Game","Great Soundtrack","Difficult","Archery"],"store_available":true,"in_store":true,"rating":{"overall":["Overwhelmingly Positive"],"recent":["Very Positive"],"updated":1697913573},"age_rating":0,"release_date":"11 Mar, 2014","url":"http:\/\/store.steampowered.com\/app\/251470\/","crossover":{"url":"<a href=\"https:\/\/www.codeweavers.com\/compatibility\/crossover\/TowerFall-Ascension\">TowerFall-Ascension<\/a>","valid":false,"compatibility":" ","breakdown":" "}}}