{"game":{"id":255520,"name":"Viscera Cleanup Detail: Shadow Warrior","type":"game","thumbnail":"https:\/\/cdn.akamai.steamstatic.com\/steam\/apps\/255520\/header.jpg?t=1666984019","genres":["Gore","Indie","Simulation"],"categories":["Single-player","Multi-player","Co-op","Shared\/Split Screen","Steam Achievements","Full controller support","Steam Cloud","Remote Play Together"],"tags":["Simulation","Gore","First-Person","Indie","Action","Blood","Comedy","Funny","Multiplayer","Singleplayer","Co-op","Casual","Short","FPS","Horror"],"store_available":true,"in_store":true,"rating":{"overall":["Mostly Positive"],"recent":["Mostly Positive"],"updated":1697863206},"age_rating":0,"release_date":"11 Oct, 2013","url":"http:\/\/store.steampowered.com\/app\/255520\/","crossover":{"url":"<a href=\"https:\/\/www.codeweavers.com\/compatibility\/crossover\/Viscera-Cleanup-Detail-Shadow-Warrior\">Viscera-Cleanup-Detail-Shadow-Warrior<\/a>","valid":true,"compatibility":"<ul class=\"star-rating-table\"><li class=\"active\"><i class=\"fas fa-star\"><\/i><\/li><li class=\"active\"><i class=\"fas fa-star\"><\/i><\/li><li class=\"active\"><i class=\"fas fa-star\"><\/i><\/li><li class=\"active\"><i class=\"fas fa-star\"><\/i><\/li><li class=\"active\"><i class=\"fas fa-star\"><\/i><\/li><\/ul><\/span>","breakdown":"\n<div class=\"container py-5\">\n    <h2 class=\"txt_magenta\"><i class=\"fad fa-medal fa-3x vertical-align-middle rotate-3deg\"><\/i> Viscera Cleanup Detail: Shadow Warrior Rating Breakdown<\/h2>\n    <span id=\"var_app_id\" class=\"noshow\">19564<\/span>\n    <span id=\"var_app_plnk\" class=\"noshow\">Viscera-Cleanup-Detail-Shadow-Warrior<\/span>\n    <p>\n        This is a breakdown of ratings by CrossOver Version.\n        The most recent version is always used on the application overview page.<br>\n        Click on a version to view ranks submitted to it.<br>\n        <a href=\"\/compatibility\/rating-system\"><i class=\"fas fa-info-circle\"><\/i> About the Rating System<\/a>\n    <\/p>\n\n\n    \n<div id=\"row_105223\" class=\"breakdown-row card card-light noshow\">\n    <div class=\"card-header showMedal cursor bold\">\n        <ul class=\"star-rating-table\"><li class=\"active\"><i class=\"fas fa-star\"><\/i><\/li><li class=\"active\"><i class=\"fas fa-star\"><\/i><\/li><li class=\"active\"><i class=\"fas fa-star\"><\/i><\/li><li class=\"active\"><i class=\"fas fa-star\"><\/i><\/li><li class=\"active\"><i class=\"fas fa-star\"><\/i><\/li><\/ul>\n        22.1.0  &middot;\n        <i class=\"fab fa-apple\"><\/i> macOS\n        <!-- but_105223 -->\n    <\/div>\n    <div id=\"area_105223\" class=\"card-body noshow\">\n        <table id=\"body_105223\" class=\"frame\" style=\"width:100%;\">\n        <\/table>\n    <\/div>\n<\/div>\n\n\n    <p class=\"mt-2\"><a href=\"#\" id=\"breakdown-showall\" class=\"noshow\"><i class=\"fas fa-chevron-square-down\"><\/i> Show More...<\/a><\/p>\n<\/div>\n<\/div>\n\n\n"}}}