{"game":{"id":29180,"name":"Osmos","type":"game","thumbnail":"https:\/\/cdn.akamai.steamstatic.com\/steam\/apps\/29180\/header.jpg?t=1602721579","genres":["Casual","Indie"],"categories":["Single-player","Steam Achievements"],"tags":["Indie","Casual","Puzzle","Relaxing","Singleplayer","Physics","Great Soundtrack","Ambient","Atmospheric","2D","Difficult","Minimalist","Space","Procedural Generation","Arcade","Strategy","Sci-fi","Science","Simulation","Education"],"store_available":true,"in_store":true,"rating":{"overall":["Very Positive"],"recent":[""],"updated":1697913121},"age_rating":0,"release_date":"18 Aug, 2009","url":"http:\/\/store.steampowered.com\/app\/29180\/","crossover":{"url":"<a href=\"https:\/\/www.codeweavers.com\/compatibility\/crossover\/Osmos\">Osmos<\/a>","valid":true,"compatibility":"<ul class=\"star-rating-table\"><li class=\"active\"><i class=\"fas fa-star\"><\/i><\/li><li class=\"active\"><i class=\"fas fa-star\"><\/i><\/li><li class=\"active\"><i class=\"fas fa-star\"><\/i><\/li><li class=\"active\"><i class=\"fas fa-star\"><\/i><\/li><li class=\"active\"><i class=\"fas fa-star\"><\/i><\/li><\/ul><\/span>","breakdown":"\n<div class=\"container py-5\">\n    <h2 class=\"txt_magenta\"><i class=\"fad fa-medal fa-3x vertical-align-middle rotate-3deg\"><\/i> Osmos Rating Breakdown<\/h2>\n    <span id=\"var_app_id\" class=\"noshow\">6362<\/span>\n    <span id=\"var_app_plnk\" class=\"noshow\">Osmos<\/span>\n    <p>\n        This is a breakdown of ratings by CrossOver Version.\n        The most recent version is always used on the application overview page.<br>\n        Click on a version to view ranks submitted to it.<br>\n        <a href=\"\/compatibility\/rating-system\"><i class=\"fas fa-info-circle\"><\/i> About the Rating System<\/a>\n    <\/p>\n\n\n    \n<div id=\"row_23653\" class=\"breakdown-row card card-light noshow\">\n    <div class=\"card-header showMedal cursor bold\">\n        <ul class=\"star-rating-table\"><li class=\"active\"><i class=\"fas fa-star\"><\/i><\/li><li class=\"active\"><i class=\"fas fa-star\"><\/i><\/li><li class=\"active\"><i class=\"fas fa-star\"><\/i><\/li><li class=\"active\"><i class=\"fas fa-star\"><\/i><\/li><li class=\"active\"><i class=\"fas fa-star\"><\/i><\/li><\/ul>\n        13.0.0  &middot;\n        <i class=\"fab fa-apple\"><\/i> macOS\n        <!-- but_23653 -->\n    <\/div>\n    <div id=\"area_23653\" class=\"card-body noshow\">\n        <table id=\"body_23653\" class=\"frame\" style=\"width:100%;\">\n        <\/table>\n    <\/div>\n<\/div>\n\n<div id=\"row_23654\" class=\"breakdown-row card card-light noshow\">\n    <div class=\"card-header showMedal cursor bold\">\n        <ul class=\"star-rating-table\"><li class=\"active\"><i class=\"fas fa-star\"><\/i><\/li><li class=\"active\"><i class=\"fas fa-star\"><\/i><\/li><li class=\"active\"><i class=\"fas fa-star\"><\/i><\/li><li class=\"active\"><i class=\"fas fa-star\"><\/i><\/li><li class=\"active\"><i class=\"fas fa-star\"><\/i><\/li><\/ul>\n        9.2.0  &middot;\n        <i class=\"fab fa-apple\"><\/i> macOS\n        <!-- but_23654 -->\n    <\/div>\n    <div id=\"area_23654\" class=\"card-body noshow\">\n        <table id=\"body_23654\" class=\"frame\" style=\"width:100%;\">\n        <\/table>\n    <\/div>\n<\/div>\n\n<div id=\"row_23656\" class=\"breakdown-row card card-light noshow\">\n    <div class=\"card-header showMedal cursor bold\">\n        <ul class=\"star-rating-table\"><li class=\"active\"><i class=\"fas fa-star\"><\/i><\/li><li class=\"active\"><i class=\"fas fa-star\"><\/i><\/li><li class=\"active\"><i class=\"fas fa-star\"><\/i><\/li><li class=\"active\"><i class=\"fas fa-star\"><\/i><\/li><li class=\"active\"><i class=\"fas fa-star\"><\/i><\/li><\/ul>\n        9.2.0  &middot;\n        <i class=\"fab fa-linux\"><\/i> Linux\n        <!-- but_23656 -->\n    <\/div>\n    <div id=\"area_23656\" class=\"card-body noshow\">\n        <table id=\"body_23656\" class=\"frame\" style=\"width:100%;\">\n        <\/table>\n    <\/div>\n<\/div>\n\n<div id=\"row_23655\" class=\"breakdown-row card card-light noshow\">\n    <div class=\"card-header showMedal cursor bold\">\n        <ul class=\"star-rating-table\"><li class=\"active\"><i class=\"fas fa-star\"><\/i><\/li><li class=\"active\"><i class=\"fas fa-star\"><\/i><\/li><li class=\"active\"><i class=\"fas fa-star\"><\/i><\/li><li class=\"active\"><i class=\"fas fa-star\"><\/i><\/li><li class=\"active\"><i class=\"fas fa-star\"><\/i><\/li><\/ul>\n        9.1.0  &middot;\n        <i class=\"fab fa-apple\"><\/i> macOS\n        <!-- but_23655 -->\n    <\/div>\n    <div id=\"area_23655\" class=\"card-body noshow\">\n        <table id=\"body_23655\" class=\"frame\" style=\"width:100%;\">\n        <\/table>\n    <\/div>\n<\/div>\n\n<div id=\"row_23657\" class=\"breakdown-row card card-light noshow\">\n    <div class=\"card-header showMedal cursor bold\">\n        <ul class=\"star-rating-table\"><li class=\"active\"><i class=\"fas fa-star\"><\/i><\/li><li class=\"active\"><i class=\"fas fa-star\"><\/i><\/li><li class=\"active\"><i class=\"fas fa-star\"><\/i><\/li><li class=\"active\"><i class=\"fas fa-star\"><\/i><\/li><li class=\"active\"><i class=\"fas fa-star\"><\/i><\/li><\/ul>\n        9.1.0  &middot;\n        <i class=\"fab fa-linux\"><\/i> Linux\n        <!-- but_23657 -->\n    <\/div>\n    <div id=\"area_23657\" class=\"card-body noshow\">\n        <table id=\"body_23657\" class=\"frame\" style=\"width:100%;\">\n        <\/table>\n    <\/div>\n<\/div>\n\n<div id=\"row_23658\" class=\"breakdown-row card card-light noshow\">\n    <div class=\"card-header showMedal cursor bold\">\n        <ul class=\"star-rating-table\"><li class=\"active\"><i class=\"fas fa-star\"><\/i><\/li><li class=\"active\"><i class=\"fas fa-star\"><\/i><\/li><li class=\"active\"><i class=\"fas fa-star\"><\/i><\/li><li class=\"active\"><i class=\"fas fa-star\"><\/i><\/li><li><i class=\"far fa-star\"><\/i><\/li><\/ul>\n        9.0.0  &middot;\n        <i class=\"fab fa-linux\"><\/i> Linux\n        <!-- but_23658 -->\n    <\/div>\n    <div id=\"area_23658\" class=\"card-body noshow\">\n        <table id=\"body_23658\" class=\"frame\" style=\"width:100%;\">\n        <\/table>\n    <\/div>\n<\/div>\n\n<div id=\"row_23659\" class=\"breakdown-row card card-light noshow\">\n    <div class=\"card-header showMedal cursor bold\">\n        <ul class=\"star-rating-table\"><li class=\"active\"><i class=\"fas fa-star\"><\/i><\/li><li class=\"active\"><i class=\"fas fa-star\"><\/i><\/li><li class=\"active\"><i class=\"fas fa-star\"><\/i><\/li><li class=\"active\"><i class=\"fas fa-star\"><\/i><\/li><li class=\"active\"><i class=\"fas fa-star\"><\/i><\/li><\/ul>\n        8.0.0  &middot;\n        <i class=\"fab fa-linux\"><\/i> Linux\n        <!-- but_23659 -->\n    <\/div>\n    <div id=\"area_23659\" class=\"card-body noshow\">\n        <table id=\"body_23659\" class=\"frame\" style=\"width:100%;\">\n        <\/table>\n    <\/div>\n<\/div>\n\n\n    <p class=\"mt-2\"><a href=\"#\" id=\"breakdown-showall\" class=\"noshow\"><i class=\"fas fa-chevron-square-down\"><\/i> Show More...<\/a><\/p>\n<\/div>\n<\/div>\n\n\n"}}}