{"game":{"id":310370,"name":"The Way of Life Free Edition","type":"game","thumbnail":"https:\/\/cdn.akamai.steamstatic.com\/steam\/apps\/310370\/header.jpg?t=1526650783","genres":["Free to Play","Indie"],"categories":["Single-player","Full controller support"],"tags":["Free to Play","Walking Simulator","Indie","First-Person","Singleplayer","Multiplayer","Adventure","Short","Simulation","Open World","Atmospheric","Survival","Great Soundtrack","Story Rich","Action","Family Friendly","Early Access","Funny","Strategy","VR"],"store_available":true,"in_store":true,"rating":{"overall":["Mostly Positive"],"recent":[""],"updated":1697924952},"age_rating":0,"release_date":"31 May, 2016","url":"http:\/\/store.steampowered.com\/app\/310370\/","crossover":{"url":"<a href=\"https:\/\/www.codeweavers.com\/compatibility\/crossover\/The-Way-of-Life-Free-Edition\">The-Way-of-Life-Free-Edition<\/a>","valid":false,"compatibility":" ","breakdown":" "}}}