{"game":{"id":327690,"name":"Gigantic","type":"game","thumbnail":"https:\/\/cdn.akamai.steamstatic.com\/steam\/apps\/327690\/header.jpg?t=1533049845","genres":["Action","Free to Play","Strategy"],"categories":["Multi-player","Online PvP","Steam Trading Cards","In-App Purchases","Partial Controller Support","Stats"],"tags":["Free to Play","Multiplayer","MOBA","Action","Strategy","Third-Person Shooter","PvP","Third Person","Co-op","Fantasy","Shooter","Massively Multiplayer","RPG","FPS","Team-Based","Adventure","Controller","Open World","Anime","Hero Shooter"],"store_available":true,"in_store":true,"rating":{"overall":["Positive"],"recent":[""],"updated":1697924982},"age_rating":0,"release_date":"19 Jul, 2017","url":"http:\/\/store.steampowered.com\/app\/327690\/","crossover":{"url":"<a href=\"https:\/\/www.codeweavers.com\/compatibility\/crossover\/Gigantic\">Gigantic<\/a>","valid":false,"compatibility":" ","breakdown":" "}}}