{"game":{"id":371200,"name":"Halcyon 6: Starbase Commander","type":"game","thumbnail":"https:\/\/cdn.akamai.steamstatic.com\/steam\/apps\/371200\/header.jpg?t=1667242181","genres":["Indie","RPG","Simulation","Strategy"],"categories":["Single-player","Steam Achievements","Steam Trading Cards","Steam Workshop","Steam Cloud"],"tags":["Strategy","Space","Indie","Pixel Graphics","Turn-Based Combat","RPG","Simulation","Base Building","Strategy RPG","Turn-Based Strategy","Singleplayer","Turn-Based","2D","Tactical RPG","Early Access","Sci-fi"],"store_available":true,"in_store":true,"rating":{"overall":["Very Positive"],"recent":[""],"updated":1697912098},"age_rating":0,"release_date":"8 Sep, 2016","url":"http:\/\/store.steampowered.com\/app\/371200\/","crossover":{"url":"<a href=\"https:\/\/www.codeweavers.com\/compatibility\/crossover\/Halcyon-6-Starbase-Commander\">Halcyon-6-Starbase-Commander<\/a>","valid":false,"compatibility":" ","breakdown":" "}}}