{"game":{"id":371420,"name":"Teddy Floppy Ear - The Race","type":"game","thumbnail":"https:\/\/cdn.akamai.steamstatic.com\/steam\/apps\/371420\/header.jpg?t=1671500243","genres":["Indie","Racing","Simulation","Sports"],"categories":["Single-player","Multi-player","Shared\/Split Screen","Steam Achievements","Full controller support","Steam Trading Cards","Steam Cloud","Steam Leaderboards","Remote Play Together"],"tags":["Racing","Sports","Indie","Family Friendly","Automobile Sim","Simulation","Multiplayer","Survival Horror","Anime","Psychological Horror","Split Screen","Sexual Content"],"store_available":true,"in_store":true,"rating":{"overall":["Mostly Positive"],"recent":[""],"updated":1697912868},"age_rating":0,"release_date":"22 May, 2015","url":"http:\/\/store.steampowered.com\/app\/371420\/","crossover":{"url":"<a href=\"https:\/\/www.codeweavers.com\/compatibility\/crossover\/Teddy-Floppy-Ear---The-Race\">Teddy-Floppy-Ear---The-Race<\/a>","valid":false,"compatibility":" ","breakdown":" "}}}