{"game":{"id":447010,"name":"Bird of Light","type":"game","thumbnail":"https:\/\/cdn.akamai.steamstatic.com\/steam\/apps\/447010\/header.jpg?t=1504045411","genres":["Action","Adventure","Casual","Indie","Strategy"],"categories":["Single-player","Steam Achievements","Steam Trading Cards","Partial Controller Support","Steam Leaderboards"],"tags":["Indie","Casual","Strategy","Adventure","Puzzle"],"store_available":true,"in_store":true,"rating":{"overall":["No user reviews"],"recent":[""],"updated":1697866271},"age_rating":0,"release_date":"15 Jul, 2016","url":"http:\/\/store.steampowered.com\/app\/447010\/","crossover":{"url":"<a href=\"https:\/\/www.codeweavers.com\/compatibility\/crossover\/Bird-of-Light\">Bird-of-Light<\/a>","valid":false,"compatibility":" ","breakdown":" "}}}