{"game":{"id":47870,"name":"Need For Speed: Hot Pursuit","type":"game","thumbnail":"https:\/\/cdn.akamai.steamstatic.com\/steam\/apps\/47870\/header.jpg?t=1615216487","genres":["Racing"],"categories":["Single-player","Multi-player","PvP","Online PvP","Steam Trading Cards","Partial Controller Support"],"tags":["Racing","Combat Racing","Sports","Driving","PvP","Automobile Sim","Open World","Arcade","Third Person","First-Person","Simulation","Atmospheric","Adventure","Online Co-Op","Multiplayer","Action","Co-op","Singleplayer","Controller","Great Soundtrack"],"store_available":true,"in_store":true,"rating":{"overall":["Very Positive"],"recent":["Very Positive"],"updated":1697911916},"age_rating":0,"release_date":"14 Dec, 2010","url":"http:\/\/store.steampowered.com\/app\/47870\/","crossover":{"url":"<a href=\"https:\/\/www.codeweavers.com\/compatibility\/crossover\/Need-For-Speed-Hot-Pursuit\">Need-For-Speed-Hot-Pursuit<\/a>","valid":true,"compatibility":"<ul class=\"star-rating-table\"><li class=\"active\"><i class=\"fas fa-star\"><\/i><\/li><li class=\"active\"><i class=\"fas fa-star\"><\/i><\/li><li class=\"active\"><i class=\"fas fa-star\"><\/i><\/li><li><i class=\"far fa-star\"><\/i><\/li><li><i class=\"far fa-star\"><\/i><\/li><\/ul><\/span>","breakdown":"\n<div class=\"container py-5\">\n    <h2 class=\"txt_magenta\"><i class=\"fad fa-medal fa-3x vertical-align-middle rotate-3deg\"><\/i> Need for Speed: Hot Pursuit Rating Breakdown<\/h2>\n    <span id=\"var_app_id\" class=\"noshow\">9279<\/span>\n    <span id=\"var_app_plnk\" class=\"noshow\">Need-For-Speed-Hot-Pursuit<\/span>\n    <p>\n        This is a breakdown of ratings by CrossOver Version.\n        The most recent version is always used on the application overview page.<br>\n        Click on a version to view ranks submitted to it.<br>\n        <a href=\"\/compatibility\/rating-system\"><i class=\"fas fa-info-circle\"><\/i> About the Rating System<\/a>\n    <\/p>\n\n\n    \n<div id=\"row_116565\" class=\"breakdown-row card card-light noshow\">\n    <div class=\"card-header showMedal cursor bold\">\n        <ul class=\"star-rating-table\"><li class=\"active\"><i class=\"fas fa-star\"><\/i><\/li><li class=\"active\"><i class=\"fas fa-star\"><\/i><\/li><li class=\"active\"><i class=\"fas fa-star\"><\/i><\/li><li><i class=\"far fa-star\"><\/i><\/li><li><i class=\"far fa-star\"><\/i><\/li><\/ul>\n        23.0.0  &middot;\n        <i class=\"fab fa-apple\"><\/i> macOS\n        <!-- but_116565 -->\n    <\/div>\n    <div id=\"area_116565\" class=\"card-body noshow\">\n        <table id=\"body_116565\" class=\"frame\" style=\"width:100%;\">\n        <\/table>\n    <\/div>\n<\/div>\n\n<div id=\"row_72908\" class=\"breakdown-row card card-light noshow\">\n    <div class=\"card-header showMedal cursor bold\">\n        <ul class=\"star-rating-table\"><li class=\"active\"><i class=\"fas fa-star\"><\/i><\/li><li class=\"active\"><i class=\"fas fa-star\"><\/i><\/li><li class=\"active\"><i class=\"fas fa-star\"><\/i><\/li><li><i class=\"far fa-star\"><\/i><\/li><li><i class=\"far fa-star\"><\/i><\/li><\/ul>\n        21.1.0  &middot;\n        <i class=\"fab fa-apple\"><\/i> macOS\n        <!-- but_72908 -->\n    <\/div>\n    <div id=\"area_72908\" class=\"card-body noshow\">\n        <table id=\"body_72908\" class=\"frame\" style=\"width:100%;\">\n        <\/table>\n    <\/div>\n<\/div>\n\n<div id=\"row_54186\" class=\"breakdown-row card card-light noshow\">\n    <div class=\"card-header showMedal cursor bold\">\n        <ul class=\"star-rating-table\"><li class=\"active\"><i class=\"fas fa-star\"><\/i><\/li><li class=\"active\"><i class=\"fas fa-star\"><\/i><\/li><li class=\"active\"><i class=\"fas fa-star\"><\/i><\/li><li class=\"active\"><i class=\"fas fa-star\"><\/i><\/li><li class=\"active\"><i class=\"fas fa-star\"><\/i><\/li><\/ul>\n        20.0.0  &middot;\n        <i class=\"fab fa-apple\"><\/i> macOS\n        <!-- but_54186 -->\n    <\/div>\n    <div id=\"area_54186\" class=\"card-body noshow\">\n        <table id=\"body_54186\" class=\"frame\" style=\"width:100%;\">\n        <\/table>\n    <\/div>\n<\/div>\n\n<div id=\"row_35867\" class=\"breakdown-row card card-light noshow\">\n    <div class=\"card-header showMedal cursor bold\">\n        <ul class=\"star-rating-table\"><li class=\"active\"><i class=\"fas fa-star\"><\/i><\/li><li class=\"active\"><i class=\"fas fa-star\"><\/i><\/li><li class=\"active\"><i class=\"fas fa-star\"><\/i><\/li><li class=\"active\"><i class=\"fas fa-star\"><\/i><\/li><li class=\"active\"><i class=\"fas fa-star\"><\/i><\/li><\/ul>\n        15.0.0  &middot;\n        <i class=\"fab fa-apple\"><\/i> macOS\n        <!-- but_35867 -->\n    <\/div>\n    <div id=\"area_35867\" class=\"card-body noshow\">\n        <table id=\"body_35867\" class=\"frame\" style=\"width:100%;\">\n        <\/table>\n    <\/div>\n<\/div>\n\n<div id=\"row_35870\" class=\"breakdown-row card card-light noshow\">\n    <div class=\"card-header showMedal cursor bold\">\n        <ul class=\"star-rating-table\"><li class=\"active\"><i class=\"fas fa-star\"><\/i><\/li><li class=\"active\"><i class=\"fas fa-star\"><\/i><\/li><li class=\"active\"><i class=\"fas fa-star\"><\/i><\/li><li class=\"active\"><i class=\"fas fa-star\"><\/i><\/li><li class=\"active\"><i class=\"fas fa-star\"><\/i><\/li><\/ul>\n        14.1.4  &middot;\n        <i class=\"fab fa-linux\"><\/i> Linux\n        <!-- but_35870 -->\n    <\/div>\n    <div id=\"area_35870\" class=\"card-body noshow\">\n        <table id=\"body_35870\" class=\"frame\" style=\"width:100%;\">\n        <\/table>\n    <\/div>\n<\/div>\n\n<div id=\"row_35868\" class=\"breakdown-row card card-light noshow\">\n    <div class=\"card-header showMedal cursor bold\">\n        <ul class=\"star-rating-table\"><li class=\"active\"><i class=\"fas fa-star\"><\/i><\/li><li class=\"active\"><i class=\"fas fa-star\"><\/i><\/li><li class=\"active\"><i class=\"fas fa-star\"><\/i><\/li><li class=\"active\"><i class=\"fas fa-star\"><\/i><\/li><li class=\"active\"><i class=\"fas fa-star\"><\/i><\/li><\/ul>\n        14.1.3  &middot;\n        <i class=\"fab fa-apple\"><\/i> macOS\n        <!-- but_35868 -->\n    <\/div>\n    <div id=\"area_35868\" class=\"card-body noshow\">\n        <table id=\"body_35868\" class=\"frame\" style=\"width:100%;\">\n        <\/table>\n    <\/div>\n<\/div>\n\n<div id=\"row_35871\" class=\"breakdown-row card card-light noshow\">\n    <div class=\"card-header showMedal cursor bold\">\n        <ul class=\"star-rating-table\"><li class=\"active\"><i class=\"fas fa-star\"><\/i><\/li><li class=\"active\"><i class=\"fas fa-star\"><\/i><\/li><li class=\"active\"><i class=\"fas fa-star\"><\/i><\/li><li class=\"active\"><i class=\"fas fa-star\"><\/i><\/li><li><i class=\"far fa-star\"><\/i><\/li><\/ul>\n        12.0.0  &middot;\n        <i class=\"fab fa-linux\"><\/i> Linux\n        <!-- but_35871 -->\n    <\/div>\n    <div id=\"area_35871\" class=\"card-body noshow\">\n        <table id=\"body_35871\" class=\"frame\" style=\"width:100%;\">\n        <\/table>\n    <\/div>\n<\/div>\n\n<div id=\"row_35869\" class=\"breakdown-row card card-light noshow\">\n    <div class=\"card-header showMedal cursor bold\">\n        <ul class=\"star-rating-table\"><li class=\"active\"><i class=\"fas fa-star\"><\/i><\/li><li class=\"active\"><i class=\"fas fa-star\"><\/i><\/li><li class=\"active\"><i class=\"fas fa-star\"><\/i><\/li><li class=\"active\"><i class=\"fas fa-star\"><\/i><\/li><li><i class=\"far fa-star\"><\/i><\/li><\/ul>\n        11.2.0  &middot;\n        <i class=\"fab fa-apple\"><\/i> macOS\n        <!-- but_35869 -->\n    <\/div>\n    <div id=\"area_35869\" class=\"card-body noshow\">\n        <table id=\"body_35869\" class=\"frame\" style=\"width:100%;\">\n        <\/table>\n    <\/div>\n<\/div>\n\n<div id=\"row_35872\" class=\"breakdown-row card card-light noshow\">\n    <div class=\"card-header showMedal cursor bold\">\n        <ul class=\"star-rating-table\"><li class=\"active\"><i class=\"fas fa-star\"><\/i><\/li><li class=\"active\"><i class=\"fas fa-star\"><\/i><\/li><li class=\"active\"><i class=\"fas fa-star\"><\/i><\/li><li><i class=\"far fa-star\"><\/i><\/li><li><i class=\"far fa-star\"><\/i><\/li><\/ul>\n        11.2.0  &middot;\n        <i class=\"fab fa-linux\"><\/i> Linux\n        <!-- but_35872 -->\n    <\/div>\n    <div id=\"area_35872\" class=\"card-body noshow\">\n        <table id=\"body_35872\" class=\"frame\" style=\"width:100%;\">\n        <\/table>\n    <\/div>\n<\/div>\n\n\n    <p class=\"mt-2\"><a href=\"#\" id=\"breakdown-showall\" class=\"noshow\"><i class=\"fas fa-chevron-square-down\"><\/i> Show More...<\/a><\/p>\n<\/div>\n<\/div>\n\n\n"}}}