{"game":{"id":712190,"name":"Genesis Alpha One Deluxe Edition","type":"game","thumbnail":"https:\/\/cdn.akamai.steamstatic.com\/steam\/apps\/712190\/header.jpg?t=1668769973","genres":["Action","Adventure","Indie","RPG","Simulation"],"categories":["Single-player","Steam Achievements","Full controller support","Steam Cloud","Remote Play on TV"],"tags":["Sci-fi","Action Roguelike","FPS","Base Building","Open World","Roguelite","Horror","Management","Building","Space Sim","Survival","Roguelike","First-Person","3D","Space","Post-apocalyptic","Procedural Generation","Multiple Endings","Survival Horror","Action"],"store_available":true,"in_store":true,"rating":{"overall":["Mostly Positive"],"recent":[""],"updated":1697870133},"age_rating":0,"release_date":"25 Feb, 2020","url":"http:\/\/store.steampowered.com\/app\/712190\/","crossover":{"url":"<a href=\"https:\/\/www.codeweavers.com\/compatibility\/crossover\/Genesis-Alpha-One-Deluxe-Edition\">Genesis-Alpha-One-Deluxe-Edition<\/a>","valid":true,"compatibility":"<ul class=\"star-rating-table\"><li class=\"active\"><i class=\"fas fa-star\"><\/i><\/li><li class=\"active\"><i class=\"fas fa-star\"><\/i><\/li><li class=\"active\"><i class=\"fas fa-star\"><\/i><\/li><li><i class=\"far fa-star\"><\/i><\/li><li><i class=\"far fa-star\"><\/i><\/li><\/ul><\/span>","breakdown":"\n<div class=\"container py-5\">\n    <h2 class=\"txt_magenta\"><i class=\"fad fa-medal fa-3x vertical-align-middle rotate-3deg\"><\/i> Genesis Alpha One Deluxe Edition Rating Breakdown<\/h2>\n    <span id=\"var_app_id\" class=\"noshow\">18479<\/span>\n    <span id=\"var_app_plnk\" class=\"noshow\">Genesis-Alpha-One-Deluxe-Edition<\/span>\n    <p>\n        This is a breakdown of ratings by CrossOver Version.\n        The most recent version is always used on the application overview page.<br>\n        Click on a version to view ranks submitted to it.<br>\n        <a href=\"\/compatibility\/rating-system\"><i class=\"fas fa-info-circle\"><\/i> About the Rating System<\/a>\n    <\/p>\n\n\n    \n<div id=\"row_95080\" class=\"breakdown-row card card-light noshow\">\n    <div class=\"card-header showMedal cursor bold\">\n        <ul class=\"star-rating-table\"><li class=\"active\"><i class=\"fas fa-star\"><\/i><\/li><li class=\"active\"><i class=\"fas fa-star\"><\/i><\/li><li class=\"active\"><i class=\"fas fa-star\"><\/i><\/li><li><i class=\"far fa-star\"><\/i><\/li><li><i class=\"far fa-star\"><\/i><\/li><\/ul>\n        22.0.1  &middot;\n        <i class=\"fab fa-apple\"><\/i> macOS\n        <!-- but_95080 -->\n    <\/div>\n    <div id=\"area_95080\" class=\"card-body noshow\">\n        <table id=\"body_95080\" class=\"frame\" style=\"width:100%;\">\n        <\/table>\n    <\/div>\n<\/div>\n\n<div id=\"row_84959\" class=\"breakdown-row card card-light noshow\">\n    <div class=\"card-header showMedal cursor bold\">\n        <ul class=\"star-rating-table\"><li class=\"active\"><i class=\"fas fa-star\"><\/i><\/li><li class=\"active\"><i class=\"fas fa-star\"><\/i><\/li><li class=\"active\"><i class=\"fas fa-star\"><\/i><\/li><li><i class=\"far fa-star\"><\/i><\/li><li><i class=\"far fa-star\"><\/i><\/li><\/ul>\n        21.1.0  &middot;\n        <i class=\"fab fa-apple\"><\/i> macOS\n        <!-- but_84959 -->\n    <\/div>\n    <div id=\"area_84959\" class=\"card-body noshow\">\n        <table id=\"body_84959\" class=\"frame\" style=\"width:100%;\">\n        <\/table>\n    <\/div>\n<\/div>\n\n\n    <p class=\"mt-2\"><a href=\"#\" id=\"breakdown-showall\" class=\"noshow\"><i class=\"fas fa-chevron-square-down\"><\/i> Show More...<\/a><\/p>\n<\/div>\n<\/div>\n\n\n"}}}