{"game":{"id":739630,"name":"Phasmophobia","type":"game","thumbnail":"https:\/\/cdn.akamai.steamstatic.com\/steam\/apps\/739630\/header.jpg?t=1693954450","genres":["Action","Indie","Early Access"],"categories":["Single-player","Multi-player","Co-op","Online Co-op","Full controller support","Tracked Controller Support","Steam Cloud","Remote Play on Phone","Remote Play on Tablet"],"tags":["Horror","Online Co-Op","Multiplayer","Psychological Horror","Co-op","VR","Supernatural","First-Person","Investigation","Dark","Demons","Mystery","Detective","Early Access","3D","Thriller","Indie","Action","Tactical","Lovecraftian"],"store_available":true,"in_store":true,"rating":{"overall":["Overwhelmingly Positive"],"recent":["Very Positive"],"updated":1697913309},"age_rating":0,"release_date":"18 Sep, 2020","url":"http:\/\/store.steampowered.com\/app\/739630\/","crossover":{"url":"<a href=\"https:\/\/www.codeweavers.com\/compatibility\/crossover\/Phasmophobia\">Phasmophobia<\/a>","valid":true,"compatibility":"<ul class=\"star-rating-table\"><li class=\"active\"><i class=\"fas fa-star\"><\/i><\/li><li class=\"active\"><i class=\"fas fa-star\"><\/i><\/li><li class=\"active\"><i class=\"fas fa-star\"><\/i><\/li><li class=\"active\"><i class=\"fas fa-star\"><\/i><\/li><li class=\"active\"><i class=\"fas fa-star\"><\/i><\/li><\/ul><\/span>","breakdown":"\n<div class=\"container py-5\">\n    <h2 class=\"txt_magenta\"><i class=\"fad fa-medal fa-3x vertical-align-middle rotate-3deg\"><\/i> Phasmophobia Rating Breakdown<\/h2>\n    <span id=\"var_app_id\" class=\"noshow\">16772<\/span>\n    <span id=\"var_app_plnk\" class=\"noshow\">Phasmophobia<\/span>\n    <p>\n        This is a breakdown of ratings by CrossOver Version.\n        The most recent version is always used on the application overview page.<br>\n        Click on a version to view ranks submitted to it.<br>\n        <a href=\"\/compatibility\/rating-system\"><i class=\"fas fa-info-circle\"><\/i> About the Rating System<\/a>\n    <\/p>\n\n\n    \n<div id=\"row_122339\" class=\"breakdown-row card card-light noshow\">\n    <div class=\"card-header showMedal cursor bold\">\n        <ul class=\"star-rating-table\"><li class=\"active\"><i class=\"fas fa-star\"><\/i><\/li><li class=\"active\"><i class=\"fas fa-star\"><\/i><\/li><li class=\"active\"><i class=\"fas fa-star\"><\/i><\/li><li class=\"active\"><i class=\"fas fa-star\"><\/i><\/li><li class=\"active\"><i class=\"fas fa-star\"><\/i><\/li><\/ul>\n        23.6.0  &middot;\n        <i class=\"fab fa-apple\"><\/i> macOS\n        <!-- but_122339 -->\n    <\/div>\n    <div id=\"area_122339\" class=\"card-body noshow\">\n        <table id=\"body_122339\" class=\"frame\" style=\"width:100%;\">\n        <\/table>\n    <\/div>\n<\/div>\n\n<div id=\"row_121555\" class=\"breakdown-row card card-light noshow\">\n    <div class=\"card-header showMedal cursor bold\">\n        <ul class=\"star-rating-table\"><li class=\"active\"><i class=\"fas fa-star\"><\/i><\/li><li class=\"active\"><i class=\"fas fa-star\"><\/i><\/li><li class=\"active\"><i class=\"fas fa-star\"><\/i><\/li><li class=\"active\"><i class=\"fas fa-star\"><\/i><\/li><li><i class=\"far fa-star\"><\/i><\/li><\/ul>\n        23.5.0  &middot;\n        <i class=\"fab fa-apple\"><\/i> macOS\n        <!-- but_121555 -->\n    <\/div>\n    <div id=\"area_121555\" class=\"card-body noshow\">\n        <table id=\"body_121555\" class=\"frame\" style=\"width:100%;\">\n        <\/table>\n    <\/div>\n<\/div>\n\n<div id=\"row_115223\" class=\"breakdown-row card card-light noshow\">\n    <div class=\"card-header showMedal cursor bold\">\n        <ul class=\"star-rating-table\"><li class=\"active\"><i class=\"fas fa-star\"><\/i><\/li><li class=\"active\"><i class=\"fas fa-star\"><\/i><\/li><li class=\"active\"><i class=\"fas fa-star\"><\/i><\/li><li class=\"active\"><i class=\"fas fa-star\"><\/i><\/li><li><i class=\"far fa-star\"><\/i><\/li><\/ul>\n        22.1.1  &middot;\n        <i class=\"fab fa-apple\"><\/i> macOS\n        <!-- but_115223 -->\n    <\/div>\n    <div id=\"area_115223\" class=\"card-body noshow\">\n        <table id=\"body_115223\" class=\"frame\" style=\"width:100%;\">\n        <\/table>\n    <\/div>\n<\/div>\n\n<div id=\"row_105372\" class=\"breakdown-row card card-light noshow\">\n    <div class=\"card-header showMedal cursor bold\">\n        <ul class=\"star-rating-table\"><li class=\"active\"><i class=\"fas fa-star\"><\/i><\/li><li class=\"active\"><i class=\"fas fa-star\"><\/i><\/li><li class=\"active\"><i class=\"fas fa-star\"><\/i><\/li><li class=\"active\"><i class=\"fas fa-star\"><\/i><\/li><li class=\"active\"><i class=\"fas fa-star\"><\/i><\/li><\/ul>\n        22.1.0  &middot;\n        <i class=\"fab fa-apple\"><\/i> macOS\n        <!-- but_105372 -->\n    <\/div>\n    <div id=\"area_105372\" class=\"card-body noshow\">\n        <table id=\"body_105372\" class=\"frame\" style=\"width:100%;\">\n        <\/table>\n    <\/div>\n<\/div>\n\n<div id=\"row_107210\" class=\"breakdown-row card card-light noshow\">\n    <div class=\"card-header showMedal cursor bold\">\n        <ul class=\"star-rating-table\"><li class=\"active\"><i class=\"fas fa-star\"><\/i><\/li><li class=\"active\"><i class=\"fas fa-star\"><\/i><\/li><li class=\"active\"><i class=\"fas fa-star\"><\/i><\/li><li class=\"active\"><i class=\"fas fa-star\"><\/i><\/li><li class=\"active\"><i class=\"fas fa-star\"><\/i><\/li><\/ul>\n        22.0.1  &middot;\n        <i class=\"fab fa-apple\"><\/i> macOS\n        <!-- but_107210 -->\n    <\/div>\n    <div id=\"area_107210\" class=\"card-body noshow\">\n        <table id=\"body_107210\" class=\"frame\" style=\"width:100%;\">\n        <\/table>\n    <\/div>\n<\/div>\n\n<div id=\"row_94142\" class=\"breakdown-row card card-light noshow\">\n    <div class=\"card-header showMedal cursor bold\">\n        <ul class=\"star-rating-table\"><li class=\"active\"><i class=\"fas fa-star\"><\/i><\/li><li class=\"active\"><i class=\"fas fa-star\"><\/i><\/li><li class=\"active\"><i class=\"fas fa-star\"><\/i><\/li><li class=\"active\"><i class=\"fas fa-star\"><\/i><\/li><li><i class=\"far fa-star\"><\/i><\/li><\/ul>\n        22.0.0  &middot;\n        <i class=\"fab fa-apple\"><\/i> macOS\n        <!-- but_94142 -->\n    <\/div>\n    <div id=\"area_94142\" class=\"card-body noshow\">\n        <table id=\"body_94142\" class=\"frame\" style=\"width:100%;\">\n        <\/table>\n    <\/div>\n<\/div>\n\n<div id=\"row_91074\" class=\"breakdown-row card card-light noshow\">\n    <div class=\"card-header showMedal cursor bold\">\n        <ul class=\"star-rating-table\"><li class=\"active\"><i class=\"fas fa-star\"><\/i><\/li><li class=\"active\"><i class=\"fas fa-star\"><\/i><\/li><li class=\"active\"><i class=\"fas fa-star\"><\/i><\/li><li class=\"active\"><i class=\"fas fa-star\"><\/i><\/li><li><i class=\"far fa-star\"><\/i><\/li><\/ul>\n        21.2.0  &middot;\n        <i class=\"fab fa-apple\"><\/i> macOS\n        <!-- but_91074 -->\n    <\/div>\n    <div id=\"area_91074\" class=\"card-body noshow\">\n        <table id=\"body_91074\" class=\"frame\" style=\"width:100%;\">\n        <\/table>\n    <\/div>\n<\/div>\n\n<div id=\"row_68321\" class=\"breakdown-row card card-light noshow\">\n    <div class=\"card-header showMedal cursor bold\">\n        <ul class=\"star-rating-table\"><li class=\"active\"><i class=\"fas fa-star\"><\/i><\/li><li class=\"active\"><i class=\"fas fa-star\"><\/i><\/li><li><i class=\"far fa-star\"><\/i><\/li><li><i class=\"far fa-star\"><\/i><\/li><li><i class=\"far fa-star\"><\/i><\/li><\/ul>\n        21.1.0  &middot;\n        <i class=\"fab fa-apple\"><\/i> macOS\n        <!-- but_68321 -->\n    <\/div>\n    <div id=\"area_68321\" class=\"card-body noshow\">\n        <table id=\"body_68321\" class=\"frame\" style=\"width:100%;\">\n        <\/table>\n    <\/div>\n<\/div>\n\n<div id=\"row_64324\" class=\"breakdown-row card card-light noshow\">\n    <div class=\"card-header showMedal cursor bold\">\n        <ul class=\"star-rating-table\"><li class=\"active\"><i class=\"fas fa-star\"><\/i><\/li><li class=\"active\"><i class=\"fas fa-star\"><\/i><\/li><li class=\"active\"><i class=\"fas fa-star\"><\/i><\/li><li><i class=\"far fa-star\"><\/i><\/li><li><i class=\"far fa-star\"><\/i><\/li><\/ul>\n        21.0.0  &middot;\n        <i class=\"fab fa-apple\"><\/i> macOS\n        <!-- but_64324 -->\n    <\/div>\n    <div id=\"area_64324\" class=\"card-body noshow\">\n        <table id=\"body_64324\" class=\"frame\" style=\"width:100%;\">\n        <\/table>\n    <\/div>\n<\/div>\n\n<div id=\"row_55168\" class=\"breakdown-row card card-light noshow\">\n    <div class=\"card-header showMedal cursor bold\">\n        <ul class=\"star-rating-table\"><li class=\"active\"><i class=\"fas fa-star\"><\/i><\/li><li class=\"active\"><i class=\"fas fa-star\"><\/i><\/li><li class=\"active\"><i class=\"fas fa-star\"><\/i><\/li><li class=\"active\"><i class=\"fas fa-star\"><\/i><\/li><li><i class=\"far fa-star\"><\/i><\/li><\/ul>\n        20.0.2  &middot;\n        <i class=\"fab fa-apple\"><\/i> macOS\n        <!-- but_55168 -->\n    <\/div>\n    <div id=\"area_55168\" class=\"card-body noshow\">\n        <table id=\"body_55168\" class=\"frame\" style=\"width:100%;\">\n        <\/table>\n    <\/div>\n<\/div>\n\n\n    <p class=\"mt-2\"><a href=\"#\" id=\"breakdown-showall\" class=\"noshow\"><i class=\"fas fa-chevron-square-down\"><\/i> Show More...<\/a><\/p>\n<\/div>\n<\/div>\n\n\n"}}}