{"game":{"id":765900,"name":"Leisure Suit Larry - Magna Cum Laude Uncut and Uncensored","type":"game","thumbnail":"https:\/\/cdn.akamai.steamstatic.com\/steam\/apps\/765900\/header.jpg?t=1596471970","genres":["Adventure"],"categories":["Single-player"],"tags":["Sexual Content","Nudity","Adventure","Mature","Comedy","Singleplayer","Point &amp; Click","NSFW","Funny"],"store_available":true,"in_store":true,"rating":{"overall":["Mostly Positive"],"recent":[""],"updated":1697870308},"age_rating":0,"release_date":"18 Dec, 2017","url":"http:\/\/store.steampowered.com\/app\/765900\/","crossover":{"url":"<a href=\"https:\/\/www.codeweavers.com\/compatibility\/crossover\/Leisure-Suit-Larry---Magna-Cum-Laude-Uncut-and-Uncensored\">Leisure-Suit-Larry---Magna-Cum-Laude-Uncut-and-Uncensored<\/a>","valid":false,"compatibility":" ","breakdown":" "}}}