{"game":{"id":777770,"name":"WAR PARTY","type":"game","thumbnail":"https:\/\/cdn.akamai.steamstatic.com\/steam\/apps\/777770\/header.jpg?t=1689602954","genres":["Strategy"],"categories":["Single-player","Multi-player","PvP","Online PvP","Steam Achievements","Steam Trading Cards","Steam Cloud","Steam Leaderboards"],"tags":["Strategy","RTS","Base Building","Real-Time","Resource Management","War","Historical","Dinosaurs","City Builder","Tactical","Management","Grand Strategy","Replay Value","Top-Down","Singleplayer","Multiplayer","Fantasy","PvP","Competitive","Classic"],"store_available":true,"in_store":true,"rating":{"overall":["Mixed"],"recent":[""],"updated":1697870466},"age_rating":0,"release_date":"28 Mar, 2019","url":"http:\/\/store.steampowered.com\/app\/777770\/","crossover":{"url":"<a href=\"https:\/\/www.codeweavers.com\/compatibility\/crossover\/WAR-PARTY\">WAR-PARTY<\/a>","valid":false,"compatibility":" ","breakdown":" "}}}