{"game":{"id":835950,"name":"Transpose","type":"game","thumbnail":"https:\/\/cdn.akamai.steamstatic.com\/steam\/apps\/835950\/header.jpg?t=1685535328","genres":["Action","Casual"],"categories":["Single-player","Steam Achievements","Tracked Controller Support","VR Only"],"tags":["VR","Puzzle Platformer","Puzzle","Time Manipulation","Exploration","Surreal","Physics","Time Management","Relaxing","Strategy","Casual","First-Person","Stylized","Time Travel","Psychedelic","Atmospheric","Singleplayer","Action","Sci-fi","Cult Classic"],"store_available":true,"in_store":true,"rating":{"overall":["Very Positive"],"recent":[""],"updated":1698036944},"age_rating":0,"release_date":"6 Nov, 2018","url":"http:\/\/store.steampowered.com\/app\/835950\/","crossover":{"url":"<a href=\"https:\/\/www.codeweavers.com\/compatibility\/crossover\/Transpose\">Transpose<\/a>","valid":false,"compatibility":" ","breakdown":" "}}}