{"game":{"id":999220,"name":"Amnesia: Rebirth","type":"game","thumbnail":"https:\/\/cdn.akamai.steamstatic.com\/steam\/apps\/999220\/header.jpg?t=1685698954","genres":["Adventure","Indie"],"categories":["Single-player","Steam Achievements","Full controller support","Steam Workshop","Includes level editor","Remote Play on TV","Remote Play Together"],"tags":["Horror","Survival Horror","Psychological Horror","Atmospheric","Gore","First-Person","Puzzle","Nudity","Story Rich","Lovecraftian","Dark","Adventure","Indie","Singleplayer","Action","Exploration","Female Protagonist","Walking Simulator","Stealth","Physics"],"store_available":true,"in_store":true,"rating":{"overall":["Mostly Positive"],"recent":["Mostly Positive"],"updated":1697871480},"age_rating":0,"release_date":"20 Oct, 2020","url":"http:\/\/store.steampowered.com\/app\/999220\/","crossover":{"url":"<a href=\"https:\/\/www.codeweavers.com\/compatibility\/crossover\/Amnesia-Rebirth\">Amnesia-Rebirth<\/a>","valid":true,"compatibility":"<ul class=\"star-rating-table\"><li class=\"active\"><i class=\"fas fa-star\"><\/i><\/li><li class=\"active\"><i class=\"fas fa-star\"><\/i><\/li><li><i class=\"far fa-star\"><\/i><\/li><li><i class=\"far fa-star\"><\/i><\/li><li><i class=\"far fa-star\"><\/i><\/li><\/ul><\/span>","breakdown":"\n<div class=\"container py-5\">\n    <h2 class=\"txt_magenta\"><i class=\"fad fa-medal fa-3x vertical-align-middle rotate-3deg\"><\/i> Amnesia: Rebirth Rating Breakdown<\/h2>\n    <span id=\"var_app_id\" class=\"noshow\">17493<\/span>\n    <span id=\"var_app_plnk\" class=\"noshow\">Amnesia-Rebirth<\/span>\n    <p>\n        This is a breakdown of ratings by CrossOver Version.\n        The most recent version is always used on the application overview page.<br>\n        Click on a version to view ranks submitted to it.<br>\n        <a href=\"\/compatibility\/rating-system\"><i class=\"fas fa-info-circle\"><\/i> About the Rating System<\/a>\n    <\/p>\n\n\n    \n<div id=\"row_97204\" class=\"breakdown-row card card-light noshow\">\n    <div class=\"card-header showMedal cursor bold\">\n        <ul class=\"star-rating-table\"><li class=\"active\"><i class=\"fas fa-star\"><\/i><\/li><li class=\"active\"><i class=\"fas fa-star\"><\/i><\/li><li><i class=\"far fa-star\"><\/i><\/li><li><i class=\"far fa-star\"><\/i><\/li><li><i class=\"far fa-star\"><\/i><\/li><\/ul>\n        22.0.1  &middot;\n        <i class=\"fab fa-apple\"><\/i> macOS\n        <!-- but_97204 -->\n    <\/div>\n    <div id=\"area_97204\" class=\"card-body noshow\">\n        <table id=\"body_97204\" class=\"frame\" style=\"width:100%;\">\n        <\/table>\n    <\/div>\n<\/div>\n\n<div id=\"row_74024\" class=\"breakdown-row card card-light noshow\">\n    <div class=\"card-header showMedal cursor bold\">\n        <ul class=\"star-rating-table\"><li class=\"active\"><i class=\"fas fa-star\"><\/i><\/li><li class=\"active\"><i class=\"fas fa-star\"><\/i><\/li><li><i class=\"far fa-star\"><\/i><\/li><li><i class=\"far fa-star\"><\/i><\/li><li><i class=\"far fa-star\"><\/i><\/li><\/ul>\n        21.2.0  &middot;\n        <i class=\"fab fa-apple\"><\/i> macOS\n        <!-- but_74024 -->\n    <\/div>\n    <div id=\"area_74024\" class=\"card-body noshow\">\n        <table id=\"body_74024\" class=\"frame\" style=\"width:100%;\">\n        <\/table>\n    <\/div>\n<\/div>\n\n<div id=\"row_60673\" class=\"breakdown-row card card-light noshow\">\n    <div class=\"card-header showMedal cursor bold\">\n        <ul class=\"star-rating-table\"><li class=\"active\"><i class=\"fas fa-star\"><\/i><\/li><li class=\"active\"><i class=\"fas fa-star\"><\/i><\/li><li><i class=\"far fa-star\"><\/i><\/li><li><i class=\"far fa-star\"><\/i><\/li><li><i class=\"far fa-star\"><\/i><\/li><\/ul>\n        21.0.0  &middot;\n        <i class=\"fab fa-apple\"><\/i> macOS\n        <!-- but_60673 -->\n    <\/div>\n    <div id=\"area_60673\" class=\"card-body noshow\">\n        <table id=\"body_60673\" class=\"frame\" style=\"width:100%;\">\n        <\/table>\n    <\/div>\n<\/div>\n\n<div id=\"row_60604\" class=\"breakdown-row card card-light noshow\">\n    <div class=\"card-header showMedal cursor bold\">\n        <ul class=\"star-rating-table\"><li class=\"active\"><i class=\"fas fa-star\"><\/i><\/li><li class=\"active\"><i class=\"fas fa-star\"><\/i><\/li><li><i class=\"far fa-star\"><\/i><\/li><li><i class=\"far fa-star\"><\/i><\/li><li><i class=\"far fa-star\"><\/i><\/li><\/ul>\n        20.0.4  &middot;\n        <i class=\"fab fa-apple\"><\/i> macOS\n        <!-- but_60604 -->\n    <\/div>\n    <div id=\"area_60604\" class=\"card-body noshow\">\n        <table id=\"body_60604\" class=\"frame\" style=\"width:100%;\">\n        <\/table>\n    <\/div>\n<\/div>\n\n\n    <p class=\"mt-2\"><a href=\"#\" id=\"breakdown-showall\" class=\"noshow\"><i class=\"fas fa-chevron-square-down\"><\/i> Show More...<\/a><\/p>\n<\/div>\n<\/div>\n\n\n"}}}